LICENSE.rst
MANIFEST.in
NEWS.rst
README.rst
setup.cfg
setup.py
src/docutils_react_docgen/__init__.py
src/docutils_react_docgen/docutils_react_docgen.py
src/docutils_react_docgen.egg-info/PKG-INFO
src/docutils_react_docgen.egg-info/SOURCES.txt
src/docutils_react_docgen.egg-info/dependency_links.txt
src/docutils_react_docgen.egg-info/requires.txt
src/docutils_react_docgen.egg-info/top_level.txt