Metadata-Version: 1.1
Name: docutils-react-docgen
Version: 0.4.0
Summary: docutils extension which converts react-docgen output to restructured text
Home-page: https://bitbucket.org/pwexler/docutils_react_docgen
Author: Paul Wexler
Author-email: paul@prometheusresearch.com
License: MIT
Keywords: docutils,sphinx,react,docgen,documentation
Platform: Any
Classifier: Programming Language :: Python
Classifier: Intended Audience :: Developers
